{
    "asset": {
        "format": "jpg",
        "id": "814deac14a40b8f506345c82aaf5d9d3",
        "name": "9-5.jpg",
        "path": "file:/Users/macbookair/Documents/2019_develop/DIA/bingata-annotation/img/9-5.jpg",
        "size": {
            "width": 600,
            "height": 600
        },
        "state": 2,
        "type": 1
    },
    "regions": [
        {
            "id": "PpKo4DLxT",
            "type": "RECTANGLE",
            "tags": [
                "flower"
            ],
            "boundingBox": {
                "height": 63.60102953410982,
                "width": 61.877339850249584,
                "left": 89.71765806988353,
                "top": 0.35877703826955076
            },
            "points": [
                {
                    "x": 89.71765806988353,
                    "y": 0.35877703826955076
                },
                {
                    "x": 151.59499792013312,
                    "y": 0.35877703826955076
                },
                {
                    "x": 151.59499792013312,
                    "y": 63.95980657237937
                },
                {
                    "x": 89.71765806988353,
                    "y": 63.95980657237937
                }
            ]
        },
        {
            "id": "CAYuB6aF6",
            "type": "RECTANGLE",
            "tags": [
                "flower"
            ],
            "boundingBox": {
                "height": 77.00837146422629,
                "width": 69.91472545757071,
                "left": 238.23965266222962,
                "top": 50.954138935108155
            },
            "points": [
                {
                    "x": 238.23965266222962,
                    "y": 50.954138935108155
                },
                {
                    "x": 308.15437811980036,
                    "y": 50.954138935108155
                },
                {
                    "x": 308.15437811980036,
                    "y": 127.96251039933445
                },
                {
                    "x": 238.23965266222962,
                    "y": 127.96251039933445
                }
            ]
        },
        {
            "id": "tgXO_ad2H",
            "type": "RECTANGLE",
            "tags": [
                "flower"
            ],
            "boundingBox": {
                "height": 67.68796797004991,
                "width": 61.90853785357737,
                "left": 419.4415557404326,
                "top": 101.87318011647254
            },
            "points": [
                {
                    "x": 419.4415557404326,
                    "y": 101.87318011647254
                },
                {
                    "x": 481.35009359401,
                    "y": 101.87318011647254
                },
                {
                    "x": 481.35009359401,
                    "y": 169.56114808652245
                },
                {
                    "x": 419.4415557404326,
                    "y": 169.56114808652245
                }
            ]
        },
        {
            "id": "VyWkUr_Ue",
            "type": "RECTANGLE",
            "tags": [
                "flower"
            ],
            "boundingBox": {
                "height": 78.37718386023295,
                "width": 84.32430324459234,
                "left": 501.43380823627285,
                "top": 23.24251247920133
            },
            "points": [
                {
                    "x": 501.43380823627285,
                    "y": 23.24251247920133
                },
                {
                    "x": 585.7581114808652,
                    "y": 23.24251247920133
                },
                {
                    "x": 585.7581114808652,
                    "y": 101.61969633943427
                },
                {
                    "x": 501.43380823627285,
                    "y": 101.61969633943427
                }
            ]
        },
        {
            "id": "5gcw6AVgZ",
            "type": "RECTANGLE",
            "tags": [
                "flower"
            ],
            "boundingBox": {
                "height": 77.62843178036606,
                "width": 77.60503327787022,
                "left": 149.00946339434276,
                "top": 148.57269134775373
            },
            "points": [
                {
                    "x": 149.00946339434276,
                    "y": 148.57269134775373
                },
                {
                    "x": 226.61449667221297,
                    "y": 148.57269134775373
                },
                {
                    "x": 226.61449667221297,
                    "y": 226.2011231281198
                },
                {
                    "x": 149.00946339434276,
                    "y": 226.2011231281198
                }
            ]
        },
        {
            "id": "Z80ECDNXB",
            "type": "RECTANGLE",
            "tags": [
                "flower"
            ],
            "boundingBox": {
                "height": 141.93921589018302,
                "width": 133.18817595673877,
                "left": 459.6557820299501,
                "top": 332.079346921797
            },
            "points": [
                {
                    "x": 459.6557820299501,
                    "y": 332.079346921797
                },
                {
                    "x": 592.8439579866889,
                    "y": 332.079346921797
                },
                {
                    "x": 592.8439579866889,
                    "y": 474.01856281198
                },
                {
                    "x": 459.6557820299501,
                    "y": 474.01856281198
                }
            ]
        },
        {
            "id": "1_RFihGKy",
            "type": "RECTANGLE",
            "tags": [
                "flower"
            ],
            "boundingBox": {
                "height": 132.85279742096506,
                "width": 39.07549916805324,
                "left": 560.9128015806988,
                "top": 139.91134567387687
            },
            "points": [
                {
                    "x": 560.9128015806988,
                    "y": 139.91134567387687
                },
                {
                    "x": 599.9883007487521,
                    "y": 139.91134567387687
                },
                {
                    "x": 599.9883007487521,
                    "y": 272.7641430948419
                },
                {
                    "x": 560.9128015806988,
                    "y": 272.7641430948419
                }
            ]
        },
        {
            "id": "givwR1R0S",
            "type": "RECTANGLE",
            "tags": [
                "flower"
            ],
            "boundingBox": {
                "height": 48.26331114808652,
                "width": 53.64496672212979,
                "left": 277.1630615640599,
                "top": 250.68765599001665
            },
            "points": [
                {
                    "x": 277.1630615640599,
                    "y": 250.68765599001665
                },
                {
                    "x": 330.8080282861897,
                    "y": 250.68765599001665
                },
                {
                    "x": 330.8080282861897,
                    "y": 298.9509671381032
                },
                {
                    "x": 277.1630615640599,
                    "y": 298.9509671381032
                }
            ]
        },
        {
            "id": "QHysab4pu",
            "type": "RECTANGLE",
            "tags": [
                "flower"
            ],
            "boundingBox": {
                "height": 49.81541181364393,
                "width": 52.315151830282865,
                "left": 312.5415973377704,
                "top": 316.3906509983361
            },
            "points": [
                {
                    "x": 312.5415973377704,
                    "y": 316.3906509983361
                },
                {
                    "x": 364.8567491680532,
                    "y": 316.3906509983361
                },
                {
                    "x": 364.8567491680532,
                    "y": 366.20606281198
                },
                {
                    "x": 312.5415973377704,
                    "y": 366.20606281198
                }
            ]
        },
        {
            "id": "LIlSZx_ol",
            "type": "RECTANGLE",
            "tags": [
                "flower"
            ],
            "boundingBox": {
                "height": 65.26622296173045,
                "width": 66.19826331114808,
                "left": 122.20257903494176,
                "top": 477.2631551580699
            },
            "points": [
                {
                    "x": 122.20257903494176,
                    "y": 477.2631551580699
                },
                {
                    "x": 188.40084234608986,
                    "y": 477.2631551580699
                },
                {
                    "x": 188.40084234608986,
                    "y": 542.5293781198003
                },
                {
                    "x": 122.20257903494176,
                    "y": 542.5293781198003
                }
            ]
        },
        {
            "id": "Gwkbp_6Ps",
            "type": "RECTANGLE",
            "tags": [
                "flower"
            ],
            "boundingBox": {
                "height": 52.60373336106489,
                "width": 86.82404326123128,
                "left": 2.519238768718802,
                "top": 542.8647566555741
            },
            "points": [
                {
                    "x": 2.519238768718802,
                    "y": 542.8647566555741
                },
                {
                    "x": 89.34328202995009,
                    "y": 542.8647566555741
                },
                {
                    "x": 89.34328202995009,
                    "y": 595.468490016639
                },
                {
                    "x": 2.519238768718802,
                    "y": 595.468490016639
                }
            ]
        },
        {
            "id": "jXUkUBaS2",
            "type": "RECTANGLE",
            "tags": [
                "flower"
            ],
            "boundingBox": {
                "height": 42.9050540765391,
                "width": 66.29575707154743,
                "left": 333.46765806988356,
                "top": 553.6943635607321
            },
            "points": [
                {
                    "x": 333.46765806988356,
                    "y": 553.6943635607321
                },
                {
                    "x": 399.7634151414309,
                    "y": 553.6943635607321
                },
                {
                    "x": 399.7634151414309,
                    "y": 596.5994176372712
                },
                {
                    "x": 333.46765806988356,
                    "y": 596.5994176372712
                }
            ]
        },
        {
            "id": "AiVyo9Rca",
            "type": "RECTANGLE",
            "tags": [
                "flower"
            ],
            "boundingBox": {
                "height": 63.30074875207987,
                "width": 50.770850665557404,
                "left": 549.2291493344426,
                "top": 517.1459026622297
            },
            "points": [
                {
                    "x": 549.2291493344426,
                    "y": 517.1459026622297
                },
                {
                    "x": 600,
                    "y": 517.1459026622297
                },
                {
                    "x": 600,
                    "y": 580.4466514143095
                },
                {
                    "x": 549.2291493344426,
                    "y": 580.4466514143095
                }
            ]
        }
    ],
    "version": "2.1.0"
}